mcpdoc/__init__.py
mcpdoc/_version.py
mcpdoc/cli.py
mcpdoc/main.py
mcpdoc/modal.py
mcpdoc/splash.py
modal_mcpdoc-0.1.2.dist-info/METADATA
modal_mcpdoc-0.1.2.dist-info/WHEEL
modal_mcpdoc-0.1.2.dist-info/entry_points.txt
modal_mcpdoc-0.1.2.dist-info/licenses/LICENSE
modal_mcpdoc-0.1.2.dist-info/RECORD
