Metadata-Version: 2.4
Name: modal-mcpdoc
Version: 0.1.2
Summary: MCP server for Modal Cloud documentation
License-Expression: MIT
License-File: LICENSE
Requires-Python: >=3.10
Requires-Dist: httpx>=0.28.1
Requires-Dist: markdownify>=1.1.0
Requires-Dist: mcp[cli]>=1.4.1
Requires-Dist: pyyaml>=6.0.1
